xgression_tk/__main__.py
Xgression_tk-2.6.dist-info/LICENSE
Xgression_tk-2.6.dist-info/METADATA
Xgression_tk-2.6.dist-info/WHEEL
Xgression_tk-2.6.dist-info/top_level.txt
Xgression_tk-2.6.dist-info/RECORD
