Metadata-Version: 2.1
Name: Xgression-tk
Version: 2.6
Summary: The Algorithm that find any relationship between data in equation form
Author: Thaphon Chinnakornsakul
Author-email: osunchizaza@gmail.com
License-File: LICENSE
Requires-Dist: numpy
Requires-Dist: sympy
Requires-Dist: scipy
Requires-Dist: matplotlib
Requires-Dist: xgression
